demyst/entity/__init__.py
demyst/entity/entity.py
demyst_entity-0.8.33a6.dist-info/METADATA
demyst_entity-0.8.33a6.dist-info/RECORD
demyst_entity-0.8.33a6.dist-info/WHEEL
demyst_entity-0.8.33a6.dist-info/top_level.txt
