Metadata-Version: 2.1
Name: demyst-entity
Version: 0.8.33a6
Summary: UNKNOWN
Home-page: UNKNOWN
Author: Demyst Data
Author-email: info@demystdata.com
License: UNKNOWN
Platform: UNKNOWN
Provides-Extra: testing
Provides-Extra: testing
Requires-Dist: pyspark (==2.4.4); extra == 'testing'
